graphene_generator/__init__.py
graphene_generator/holder.py
graphene_generator/__pycache__/__init__.cpython-37.pyc
graphene_generator/__pycache__/holder.cpython-37.pyc
graphene_generator-0.1.2.dist-info/LICENCE
graphene_generator-0.1.2.dist-info/METADATA
graphene_generator-0.1.2.dist-info/WHEEL
graphene_generator-0.1.2.dist-info/top_level.txt
graphene_generator-0.1.2.dist-info/RECORD
